pydecora/__init__.py
pydecora/decorators/cache.py
pydecora/decorators/retry.py
pydecora/decorators/singleton.py
pydecora/decorators/suppress.py
pydecora/decorators/timeit.py
pydecora/decorators/validate_args.py
pydecora-1.1.3.dist-info/licenses/LICENSE
tests/test_cache.py
tests/test_retry.py
tests/test_singleton.py
tests/test_suppress.py
tests/test_timeit.py
tests/test_validate_args.py
pydecora-1.1.3.dist-info/METADATA
pydecora-1.1.3.dist-info/WHEEL
pydecora-1.1.3.dist-info/top_level.txt
pydecora-1.1.3.dist-info/RECORD
