Metadata-Version: 2.4
Name: pydecora
Version: 1.1.3
Summary: A lightweight and modular Python decorator library
Author-email: Nika Sharmazanashvili <nikasharmaza@gmail.com>
License: MIT License
Project-URL: Homepage, https://github.com/nikasrmz/pydecora
Project-URL: Repository, https://github.com/nikasrmz/pydecora
Keywords: decorators,python,utilities,cache,retry,timeit
Classifier: Programming Language :: Python :: 3
Classifier: License :: OSI Approved :: MIT License
Classifier: Operating System :: OS Independent
Requires-Python: >=3.6
License-File: LICENSE
Dynamic: license-file
